oscarreports/__init__.py
oscarreports/admin.py
oscarreports/apps.py
oscarreports/forms.py
oscarreports/handlers.py
oscarreports/models.py
oscarreports/py.typed
oscarreports/tables.py
oscarreports/tasks.py
oscarreports/utils.py
oscarreports/views.py
oscarreports/locale/es/LC_MESSAGES/django.mo
oscarreports/locale/es/LC_MESSAGES/django.po
oscarreports/migrations/0001_initial.py
oscarreports/migrations/0002_alter_report_task_id.py
oscarreports/migrations/__init__.py
oscarreports/templates/oscar/dashboard/reports/index.html
oscarreports/templates/oscar/dashboard/reports/report_confirm_delete.html
oscarreports/templates/oscar/dashboard/reports/report_row_actions.html
oscarreports/templates/oscar/dashboard/reports/report_row_date_range.html
oscarreports/templates/oscar/dashboard/reports/report_row_filesize.html
oscarreports/templates/oscar/dashboard/reports/emails/report_completed_alert_body.html
oscarreports/templates/oscar/dashboard/reports/emails/report_completed_alert_body.txt
oscarreports/templates/oscar/dashboard/reports/emails/report_completed_alert_subject.txt
oscarreports/tests/__init__.py
oscarreports/tests/test_forms.py
oscarreports/tests/test_models.py
oscarreports/tests/test_tasks.py
oscarreports/tests/test_views.py
django_oscar_reports-2.5.1.dist-info/METADATA
django_oscar_reports-2.5.1.dist-info/WHEEL
django_oscar_reports-2.5.1.dist-info/licenses/LICENSE
django_oscar_reports-2.5.1.dist-info/RECORD
