Metadata-Version: 2.4
Name: django-oscar-reports
Version: 2.5.1
Summary: An extension on-top of django-oscar that improves the Oscar Dashboard's report generation system
Project-URL: Homepage, https://gitlab.com/thelabnyc/django-oscar/django-oscar-reports
Project-URL: Repository, https://gitlab.com/thelabnyc/django-oscar/django-oscar-reports
Author-email: thelab <thelabdev@thelab.co>
License: ISC
License-File: LICENSE
Requires-Python: >=3.12
Requires-Dist: django-oscar<4.1,>=4.0
Requires-Dist: django-stubs-ext>=5.1.3
Requires-Dist: django>=4.2
Provides-Extra: celery
Requires-Dist: celery>=5.5.1; extra == 'celery'
Provides-Extra: django-tasks
Requires-Dist: django-tasks>=0.8.0; extra == 'django-tasks'
